cli/VERSION.txt
cli/__init__.py
cli/soos.py
pipy_pre_release_example-1.7.1.dist-info/METADATA
pipy_pre_release_example-1.7.1.dist-info/WHEEL
pipy_pre_release_example-1.7.1.dist-info/entry_points.txt
pipy_pre_release_example-1.7.1.dist-info/top_level.txt
pipy_pre_release_example-1.7.1.dist-info/RECORD
